designer/__init__.py
designer/animation.py
designer/colors.py
designer/helpers.py
designer/keyboard.py
designer/mouse.py
designer/movement.py
designer/music.py
designer/positioning.py
designer/sfx.py
designer/system.py
designer/core/__init__.py
designer/core/clock.py
designer/core/director.py
designer/core/event.py
designer/core/internal_image.py
designer/core/scene.py
designer/core/system.py
designer/core/window.py
designer/data/colors.json
designer/data/default_key_mappings.txt
designer/data/emojis.zip
designer/data/unicode_names.json
designer/objects/__init__.py
designer/objects/arc.py
designer/objects/circle.py
designer/objects/designer_object.py
designer/objects/dialogue.py
designer/objects/ellipse.py
designer/objects/emoji.py
designer/objects/group.py
designer/objects/image.py
designer/objects/line.py
designer/objects/pen.py
designer/objects/pixels.py
designer/objects/rectangle.py
designer/objects/shape.py
designer/objects/text.py
designer/tk/__init__.py
designer/tk/dcpprint.py
designer/tk/debug.py
designer/utilities/__init__.py
designer/utilities/animation.py
designer/utilities/argument_checks.py
designer/utilities/easings.py
designer/utilities/file_system.py
designer/utilities/gif_image.py
designer/utilities/layer_tree.py
designer/utilities/memoize.py
designer/utilities/rect.py
designer/utilities/search.py
designer/utilities/util.py
designer/utilities/vector.py
designer/utilities/weak_functions.py
designer/utilities/weak_method.py
designer/utilities/weak_tuple_dictionary.py
designer-0.6.6.data/data/requirements.txt
designer-0.6.6.dist-info/LICENSE.txt
designer-0.6.6.dist-info/METADATA
designer-0.6.6.dist-info/WHEEL
designer-0.6.6.dist-info/top_level.txt
designer-0.6.6.dist-info/RECORD
