Metadata-Version: 2.1
Name: designer
Version: 0.6.6
Summary: Student-friendly and evidence-based visual graphics library.
Home-page: https://github.com/designer-edu/designer
Author: krishols, acbart
Author-email: kris@udel.edu
License: MIT
Classifier: Development Status :: 3 - Alpha
Classifier: Topic :: Education
Classifier: License :: OSI Approved :: MIT License
Classifier: Programming Language :: Python :: 3.6
Classifier: Programming Language :: Python :: 3.7
Classifier: Programming Language :: Python :: 3.8
Classifier: Programming Language :: Python :: 3.9
Requires-Python: >=3.6
License-File: LICENSE.txt
Requires-Dist: pygame >=2.0.1
Requires-Dist: Pillow >=9.0.1
